choco/__init__.py
choco/__main__.py
choco/client.py
choco/commands/__init__.py
choco/commands/apikey.py
choco/commands/config.py
choco/commands/new.py
choco/commands/pack.py
choco/commands/push.py
choco/commands/search.py
choco/config.py
choco/constants.py
choco/main.py
choco/packaging.py
choco/py.typed
choco/templates.py
choco/typing.py
choco/utils.py
chocolatey_choco-0.1.5.dist-info/METADATA
chocolatey_choco-0.1.5.dist-info/WHEEL
chocolatey_choco-0.1.5.dist-info/entry_points.txt
chocolatey_choco-0.1.5.dist-info/licenses/LICENSE.txt
chocolatey_choco-0.1.5.dist-info/RECORD
