Metadata-Version: 2.4
Name: chocolatey-choco
Version: 0.1.5
Summary: Minimal choco command for use on non-Windows platforms.
License-Expression: MIT
License-File: LICENSE.txt
Keywords: command line,windows
Author: Andrew Udvare
Author-email: audvare@gmail.com
Requires-Python: >=3.10,<4.0
Classifier: Development Status :: 4 - Beta
Classifier: Intended Audience :: Developers
Classifier: Programming Language :: Python
Classifier: Programming Language :: Python :: 3.10
Classifier: Programming Language :: Python :: 3.11
Classifier: Programming Language :: Python :: 3.12
Classifier: Programming Language :: Python :: 3.13
Classifier: Programming Language :: Python :: 3.14
Classifier: Typing :: Typed
Requires-Dist: bascom (>=0.1.0,<0.2.0)
Requires-Dist: click (>=8.3.1,<9.0.0)
Requires-Dist: defusedxml (>=0.7.1,<0.8.0)
Requires-Dist: platformdirs (>=4.5.1,<5.0.0)
Requires-Dist: python-dateutil (>=2.9.0.post0,<3.0.0)
Requires-Dist: requests (>=2.32.5,<3.0.0)
Requires-Dist: tomlkit (>=0.13.3,<0.14.0)
Requires-Dist: typing-extensions (>=4.15.0,<5.0.0)
Project-URL: Documentation, https://pychoco.readthedocs.org
Project-URL: Homepage, https://tatsh.github.io/pychoco/
Project-URL: Issues, https://github.com/Tatsh/pychoco/issues
Project-URL: Repository, https://github.com/Tatsh/pychoco
